situacao/__init__.py
situacao/__main__.py
situacao/cache.py
situacao/commands.py
situacao/data.py
situacao/minsaude.py
situacao/parse.py
situacao/pdf.py
situacao/settings.py
situacao/util.py
situacao-0.1.1.dist-info/METADATA
situacao-0.1.1.dist-info/WHEEL
situacao-0.1.1.dist-info/entry_points.txt
situacao-0.1.1.dist-info/top_level.txt
situacao-0.1.1.dist-info/RECORD
