Metadata-Version: 2.1
Name: situacao
Version: 0.1.1
Summary: A command line tool to interact with Portugal COVID-19 data.
Home-page: UNKNOWN
Author: UNKNOWN
Author-email: UNKNOWN
License: UNKNOWN
Platform: UNKNOWN
Classifier: Programming Language :: Python :: 3
Classifier: Programming Language :: Python :: 3.6
Classifier: Programming Language :: Python :: 3.7
Classifier: Programming Language :: Python :: 3.8
Requires-Dist: beautifulsoup4 (==4.9.1)
Requires-Dist: certifi (==2020.4.5.1)
Requires-Dist: chardet (==3.0.4)
Requires-Dist: idna (==2.9)
Requires-Dist: pdftotext (==2.1.4)
Requires-Dist: requests (==2.23.0)
Requires-Dist: soupsieve (==2.0.1)
Requires-Dist: urllib3 (==1.25.9)
Requires-Dist: yaspin (==0.17.0)
